fitout/__init__.py
fitout/datasources.py
fitout/helpers.py
fitout/importers/__init__.py
fitout/importers/base.py
fitout/importers/breathing_rate.py
fitout/importers/heart_rate.py
fitout/importers/sleep.py
fitout-0.1.1.dist-info/LICENSE.txt
fitout-0.1.1.dist-info/WHEEL
fitout-0.1.1.dist-info/METADATA
fitout-0.1.1.dist-info/RECORD
