Metadata-Version: 2.3
Name: fitout
Version: 0.1.1
Summary: A Python library to extract FitBit Google Takeout data.
Keywords: FitBitbit,Google Takeout,Data Processing
Author-email: Kevin Meyer <kevin@kmz.co.za>
Requires-Python: >=3.7
Classifier: Development Status :: 3 - Alpha
Classifier: Intended Audience :: Developers
Classifier: License :: OSI Approved :: GNU General Public License v3 or later (GPLv3+)
Classifier: Programming Language :: Python
Classifier: Programming Language :: Python :: 3 :: Only
Classifier: Programming Language :: Python :: 3.7
Classifier: Programming Language :: Python :: 3.8
Classifier: Programming Language :: Python :: 3.9
Classifier: Programming Language :: Python :: 3.10
Project-URL: Bug tracker, https://github.com/kev-m/FitOut/issues
Project-URL: Changelog, https://github.com/kev-m/FitOut/blob/release/CHANGELOG.md
Project-URL: Code of Conduct, https://github.com/kev-m/FitOut/blob/release/CODE_OF_CONDUCT.md
Project-URL: Contributing, https://github.com/kev-m/FitOut/blob/release/CONTRIBUTING.md
Project-URL: Home, https://github.com/kev-m/FitOut
Project-URL: Source, https://github.com/kev-m/FitOut
